things_mcp/__init__.py
things_mcp/applescript_bridge.py
things_mcp/cache.py
things_mcp/config.py
things_mcp/fast_server.py
things_mcp/formatters.py
things_mcp/handlers.py
things_mcp/logging_config.py
things_mcp/mcp_tools.py
things_mcp/simple_server.py
things_mcp/simple_url_scheme.py
things_mcp/tag_handler.py
things_mcp/things_server.py
things_mcp/url_scheme.py
things_mcp/utils.py
mseep_things3_enhanced_mcp-1.0.1.dist-info/METADATA
mseep_things3_enhanced_mcp-1.0.1.dist-info/WHEEL
mseep_things3_enhanced_mcp-1.0.1.dist-info/entry_points.txt
mseep_things3_enhanced_mcp-1.0.1.dist-info/licenses/LICENSE
mseep_things3_enhanced_mcp-1.0.1.dist-info/RECORD
